setup.py
hackpy/__init__.py
hackpy/activity.py
hackpy/admin.py
hackpy/autorun.py
hackpy/clipboard.py
hackpy/commands.py
hackpy/evil.py
hackpy/file.py
hackpy/info.py
hackpy/keyboard.py
hackpy/messagebox.py
hackpy/modules.py
hackpy/network.py
hackpy/passwords.py
hackpy/power.py
hackpy/protection.py
hackpy/python.py
hackpy/settings.py
hackpy/spy.py
hackpy/taskmanager.py
hackpy/time.py
hackpy/uac.py
hackpy.egg-info/PKG-INFO
hackpy.egg-info/SOURCES.txt
hackpy.egg-info/dependency_links.txt
hackpy.egg-info/not-zip-safe
hackpy.egg-info/requires.txt
hackpy.egg-info/top_level.txt