Metadata-Version: 1.1
Name: hackpy
Version: 0.1.7.3
Summary: The project is no longer maintained.   Full description here: https://github.com/LimerBoy/hackpy/blob/master/README.MD
Home-page: https://github.com/LimerBoy/hackpy/blob/master/README.MD
Author: LimerBoy
Author-email: LimerBoyTV@gmail.com
License: MIT
Platform: UNKNOWN
Classifier: Programming Language :: Python :: 3
Classifier: License :: OSI Approved :: MIT License
Classifier: Operating System :: Microsoft :: Windows
